Metadata-Version: 2.1
Name: django-rest-action-serializer
Version: 1.1.0
Summary: A Django app that provides a serializer mixin that allows You to customize the fieldsaccording to the action provided without the need tocreate other serializers.
Home-page: https://github.com/brunobarretofreitas/django-rest-action-serializer
Author: Bruno Barreto Freitas
Author-email: brunobarretofreitas@outlook.com
License: UNKNOWN
Download-URL: https://github.com/brunobarretofreitas/django-rest-action-serializer/archive/master.zip
Keywords: django django-rest-framework api serializer
Platform: UNKNOWN
Classifier: Development Status :: 4 - Beta
Classifier: Framework :: Django
Classifier: Intended Audience :: Developers
Classifier: Topic :: Internet :: WWW/HTTP
Classifier: License :: OSI Approved :: MIT License
Classifier: Programming Language :: Python :: 3
Classifier: Programming Language :: Python :: 3.3
Classifier: Programming Language :: Python :: 3.4
Classifier: Programming Language :: Python :: 3.5
Classifier: Programming Language :: Python :: 3.6
